[
    {
        "HomeTeamId": 1,
        "HomeTeamScore": 0,
        "AwayTeamId": 3,
        "AwayTeamScore": 0,
        "KickOffTime": "2019-11-3 17:00:56",
        "LocationOfPlay": "Stamford Bridge"
    },
    {
        "HomeTeamId": 5,
        "HomeTeamScore": 0,
        "AwayTeamId": 1,
        "AwayTeamScore": 0,
        "KickOffTime": "2020-12-3 17:00:56",
        "LocationOfPlay": "Stamford Bridge"
    },
    {
        "HomeTeamId": 4,
        "HomeTeamScore": 2,
        "AwayTeamId": 2,
        "AwayTeamScore": 2,
        "KickOffTime": "2019-1-3 17:00:56",
        "LocationOfPlay": "Stamford Bridge",
        "IsFixtureCompleted": true
    },

    {
        "HomeTeamId": 2,
        "HomeTeamScore": 6,
        "AwayTeamId": 2,
        "AwayTeamScore": 0,
        "KickOffTime": "2019-1-23 17:00:56",
        "LocationOfPlay": "Stamford Bridge",
        "IsFixtureCompleted": true        
    },
    {
        "HomeTeamId": 1,
        "HomeTeamScore": 0,
        "AwayTeamId": 4,
        "AwayTeamScore": 0,
        "KickOffTime": "2020-12-3 17:00:56",
        "LocationOfPlay": "Stamford Bridge"
        
    },
    {
        "HomeTeamId": 3,
        "HomeTeamScore": 2,
        "AwayTeamId": 4,
        "AwayTeamScore": 4,
        "KickOffTime": "2016-12-3 17:00:56",
        "LocationOfPlay": "Stamford Bridge",
        "IsFixtureCompleted": true
        
    },
    {
        "HomeTeamId": 4,
        "HomeTeamScore": 0,
        "AwayTeamId": 5,
        "AwayTeamScore": 0,
        "KickOffTime": "2020-12-3 17:00:56",
        "LocationOfPlay": "Stamford Bridge"
    },
    {
        "HomeTeamId": 1,
        "HomeTeamScore": 4,
        "AwayTeamId": 2,
        "AwayTeamScore": 0,
        "KickOffTime": "2019-2-7 17:00:56",
        "LocationOfPlay": "Stamford Bridge",
        "IsFixtureCompleted": true
    },
    {
        "HomeTeamId": 1,
        "HomeTeamScore": 2,
        "AwayTeamId": 4,
        "AwayTeamScore": 1,
        "KickOffTime": "2017-12-3 17:00:56",
        "LocationOfPlay": "Stamford Bridge",
        "IsFixtureCompleted": true
    },


    {
        "HomeTeamId": 2,
        "HomeTeamScore": 0,
        "AwayTeamId": 5,
        "AwayTeamScore": 0,
        "KickOffTime": "2020-7-3 17:00:56",
        "LocationOfPlay": "Stamford Bridge"
    },
    {
        "HomeTeamId": 3,
        "HomeTeamScore": 2,
        "AwayTeamId": 1,
        "AwayTeamScore": 0,
        "KickOffTime": "2017-12-3 17:00:56",
        "LocationOfPlay": "Stamford Bridge",
        "IsFixtureCompleted": true
    },
    {
        "HomeTeamId": 3,
        "HomeTeamScore": 2,
        "AwayTeamId": 4,
        "AwayTeamScore": 0,
        "KickOffTime": "2015-12-3 17:00:56",
        "LocationOfPlay": "Stamford Bridge",
        "IsFixtureCompleted": true
    },


    {
        "HomeTeamId": 5,
        "HomeTeamScore": 0,
        "AwayTeamId": 2,
        "AwayTeamScore": 0,
        "KickOffTime": "2020-2-3 17:00:56",
        "LocationOfPlay": "Stamford Bridge"
    },
    {
        "HomeTeamId": 5,
        "HomeTeamScore": 2,
        "AwayTeamId": 4,
        "AwayTeamScore": 2,
        "KickOffTime": "2018-12-3 17:00:56",
        "LocationOfPlay": "Stamford Bridge",
        "IsFixtureCompleted": true
    },
    {
        "HomeTeamId": 2,
        "HomeTeamScore": 2,
        "AwayTeamId": 3,
        "AwayTeamScore": 2,
        "KickOffTime": "2019-12-30 18:00:56",
        "LocationOfPlay": "Stamford Bridge",
        "IsFixtureCompleted": true
    }

]